mfm/__init__.py
mfm/mfm.py
mfm-0.1.dist-info/LICENSE.TXT
mfm-0.1.dist-info/METADATA
mfm-0.1.dist-info/WHEEL
mfm-0.1.dist-info/top_level.txt
mfm-0.1.dist-info/RECORD
