Metadata-Version: 2.1
Name: mfm
Version: 0.1
Summary: This is my First Module
Author: Salman Mumtaz
Author-email: msdsf22m007@pucit.edu.pk
Classifier: Operating System :: Microsoft :: Windows :: Windows 10
Classifier: License :: OSI Approved :: MIT License
Classifier: Programming Language :: Python :: 3
License-File: LICENSE.TXT
